simple_catalog/__init__.py
simple_catalog/__main__.py
simple_catalog/client.py
simple_catalog/database.py
simple_catalog/extractor.py
simple_catalog/hash.py
simple_catalog-0.1.2.dist-info/LICENSE
simple_catalog-0.1.2.dist-info/METADATA
simple_catalog-0.1.2.dist-info/WHEEL
simple_catalog-0.1.2.dist-info/entry_points.txt
simple_catalog-0.1.2.dist-info/top_level.txt
simple_catalog-0.1.2.dist-info/RECORD
