Metadata-Version: 2.1
Name: simple-catalog
Version: 0.1.2
Summary: Simple way to add file catalog with python
Author: hgyoon
Author-email: hgyoon@wellbia.com
Classifier: License :: OSI Approved :: MIT License
Classifier: Programming Language :: Python :: 3.11
Classifier: Programming Language :: Python :: 3.12
License-File: LICENSE
Requires-Dist: pymysql
Requires-Dist: py7zr
Requires-Dist: rarfile
